odoo9_addon_partner_phone_extension-9.0.1.0.0.99.dev6-py2.7-nspkg.pth
odoo9_addon_partner_phone_extension-9.0.1.0.0.99.dev6.dist-info/METADATA
odoo9_addon_partner_phone_extension-9.0.1.0.0.99.dev6.dist-info/RECORD
odoo9_addon_partner_phone_extension-9.0.1.0.0.99.dev6.dist-info/WHEEL
odoo9_addon_partner_phone_extension-9.0.1.0.0.99.dev6.dist-info/namespace_packages.txt
odoo9_addon_partner_phone_extension-9.0.1.0.0.99.dev6.dist-info/top_level.txt
odoo_addons/partner_phone_extension/README.rst
odoo_addons/partner_phone_extension/__init__.py
odoo_addons/partner_phone_extension/__openerp__.py
odoo_addons/partner_phone_extension/i18n/am.po
odoo_addons/partner_phone_extension/i18n/ar.po
odoo_addons/partner_phone_extension/i18n/bg.po
odoo_addons/partner_phone_extension/i18n/bs.po
odoo_addons/partner_phone_extension/i18n/ca.po
odoo_addons/partner_phone_extension/i18n/cs.po
odoo_addons/partner_phone_extension/i18n/da.po
odoo_addons/partner_phone_extension/i18n/de.po
odoo_addons/partner_phone_extension/i18n/el_GR.po
odoo_addons/partner_phone_extension/i18n/en_GB.po
odoo_addons/partner_phone_extension/i18n/es.po
odoo_addons/partner_phone_extension/i18n/es_CR.po
odoo_addons/partner_phone_extension/i18n/es_EC.po
odoo_addons/partner_phone_extension/i18n/es_MX.po
odoo_addons/partner_phone_extension/i18n/es_VE.po
odoo_addons/partner_phone_extension/i18n/et.po
odoo_addons/partner_phone_extension/i18n/eu.po
odoo_addons/partner_phone_extension/i18n/fi.po
odoo_addons/partner_phone_extension/i18n/fr.po
odoo_addons/partner_phone_extension/i18n/fr_CA.po
odoo_addons/partner_phone_extension/i18n/fr_CH.po
odoo_addons/partner_phone_extension/i18n/gl.po
odoo_addons/partner_phone_extension/i18n/hr.po
odoo_addons/partner_phone_extension/i18n/hr_HR.po
odoo_addons/partner_phone_extension/i18n/hu.po
odoo_addons/partner_phone_extension/i18n/id.po
odoo_addons/partner_phone_extension/i18n/it.po
odoo_addons/partner_phone_extension/i18n/ja.po
odoo_addons/partner_phone_extension/i18n/lt.po
odoo_addons/partner_phone_extension/i18n/lv.po
odoo_addons/partner_phone_extension/i18n/mk.po
odoo_addons/partner_phone_extension/i18n/mn.po
odoo_addons/partner_phone_extension/i18n/nb.po
odoo_addons/partner_phone_extension/i18n/nb_NO.po
odoo_addons/partner_phone_extension/i18n/nl.po
odoo_addons/partner_phone_extension/i18n/nl_BE.po
